diffy/__init__.py
diffy/_version.py
diffy/accounts.py
diffy/config.py
diffy/core.py
diffy/exceptions.py
diffy/extensions.py
diffy/filters.py
diffy/schema.py
diffy/plugins/__init__.py
diffy/plugins/base/__init__.py
diffy/plugins/base/manager.py
diffy/plugins/base/v1.py
diffy/plugins/bases/__init__.py
diffy/plugins/bases/analysis.py
diffy/plugins/bases/collection.py
diffy/plugins/bases/payload.py
diffy/plugins/bases/persistence.py
diffy/plugins/bases/target.py
diffy/plugins/diffy_aws/__init__.py
diffy/plugins/diffy_aws/auto_scaling.py
diffy/plugins/diffy_aws/plugin.py
diffy/plugins/diffy_aws/s3.py
diffy/plugins/diffy_aws/ssm.py
diffy/plugins/diffy_aws/sts.py
diffy/plugins/diffy_aws/tests/__init__.py
diffy/plugins/diffy_aws/tests/conftest.py
diffy/plugins/diffy_local/__init__.py
diffy/plugins/diffy_local/plugin.py
diffy/plugins/diffy_local/tests/__init__.py
diffy/plugins/diffy_local/tests/conftest.py
diffy/plugins/diffy_osquery/__init__.py
diffy/plugins/diffy_osquery/plugin.py
diffy/plugins/diffy_osquery/tests/__init__.py
diffy/plugins/diffy_osquery/tests/conftest.py
diffy-0.1.0.dist-info/LICENSE.txt
diffy-0.1.0.dist-info/METADATA
diffy-0.1.0.dist-info/RECORD
diffy-0.1.0.dist-info/WHEEL
diffy-0.1.0.dist-info/entry_points.txt
diffy-0.1.0.dist-info/top_level.txt
diffy_api/__init__.py
diffy_api/core.py
diffy_api/extensions.py
diffy_api/factory.py
diffy_api/schemas.py
diffy_api/common/__init__.py
diffy_api/common/health.py
diffy_api/common/util.py
diffy_api/plugins/__init__.py
diffy_api/plugins/views.py
diffy_api/tasks/__init__.py
diffy_api/tasks/views.py
diffy_cli/__init__.py
diffy_cli/core.py
diffy_cli/utils/__init__.py
diffy_cli/utils/dynamic_click.py
diffy_cli/utils/json_schema.py
tests/__init__.py
tests/conf.py
tests/conftest.py
tests/test_analysis.py
tests/test_baseline.py
